pygeoshape/__init__.py
pygeoshape/geolinestring.py
pygeoshape/geopoint.py
pygeoshape/utils.py
pygeoshape-0.0.4.dist-info/LICENSE
pygeoshape-0.0.4.dist-info/METADATA
pygeoshape-0.0.4.dist-info/WHEEL
pygeoshape-0.0.4.dist-info/top_level.txt
pygeoshape-0.0.4.dist-info/RECORD
