Metadata-Version: 2.1
Name: pygeoshape
Version: 0.0.4
Summary: A 3D geospatial package to make working with geographical & trajectory data easier in python
Home-page: https://github.com/marcbrittain/PyGeoShape
Author: Marc Brittain
Author-email: marcbrittain@yahoo.com
License: BSD 3-clause
Project-URL: Bug Tracker, https://github.com/marcbrittain/PyGeoShape/issues
Platform: UNKNOWN
Classifier: Programming Language :: Python :: 3
Classifier: License :: OSI Approved :: BSD License
Classifier: Operating System :: OS Independent
Requires-Python: >=3.6
License-File: LICENSE
Requires-Dist: shapely
Requires-Dist: matplotlib
Requires-Dist: numpy
Requires-Dist: pyproj
Requires-Dist: numba
